auto_annotate.py
generate_xml.py
label_map_util.py
protos/__init__.py
protos/string_int_label_map_pb2.py
auto_annotate-1.0.5.dist-info/LICENSE.txt
auto_annotate-1.0.5.dist-info/METADATA
auto_annotate-1.0.5.dist-info/WHEEL
auto_annotate-1.0.5.dist-info/top_level.txt
auto_annotate-1.0.5.dist-info/RECORD
