Metadata-Version: 2.1
Name: auto-annotate
Version: 1.0.5
Summary: Generate xml annotations for TensorFlow object detection models.
Home-page: https://github.com/AlvaroCavalcante/auto_annotate
Author: Alvaro Leandro Cavalcante Carneiro
Author-email: alvaroleandro250@gmail.com
License: Apache License 2.0
Download-URL: https://github.com/AlvaroCavalcante/auto_annotate
Keywords: tensorflow,python,python3,object-detection,annotation,dataset,semi-supervised,deep-learning,labeling
Platform: UNKNOWN
Classifier: Programming Language :: Python
Classifier: Programming Language :: Python :: 3
Classifier: Natural Language :: English
Classifier: Operating System :: OS Independent
Classifier: Intended Audience :: Developers
Classifier: Intended Audience :: Science/Research
Classifier: Development Status :: 5 - Production/Stable
Classifier: License :: OSI Approved :: Apache Software License
Classifier: Topic :: Scientific/Engineering :: Artificial Intelligence
Classifier: Topic :: Scientific/Engineering :: Image Processing
Classifier: Topic :: Software Development :: Libraries :: Python Modules
Requires-Python: >=3.8
Requires-Dist: Pillow (==9.3.0)
Requires-Dist: numpy (==1.22.4)
Requires-Dist: six (==1.16.0)
Requires-Dist: tensorflow (==2.11.0)
Requires-Dist: tqdm (==4.64.1)
